MANIFEST.in
README.md
VERSION
setup.cfg
setup.py
django_iglink.egg-info/PKG-INFO
django_iglink.egg-info/SOURCES.txt
django_iglink.egg-info/dependency_links.txt
django_iglink.egg-info/requires.txt
django_iglink.egg-info/top_level.txt
example/__init__.py
example/asgi.py
example/settings.py
example/urls.py
example/wsgi.py
iglink/__init__.py
iglink/admin.py
iglink/apps.py
iglink/cache.py
iglink/forms.py
iglink/models.py
iglink/scraper.py
iglink/tests.py
iglink/urls.py
iglink/views.py
iglink/migrations/0001_initial.py
iglink/migrations/__init__.py